{
    "grade": "Grade 5",
    "subject": "Science and Technology",
    "education_level": "Upper Primary",
    "strands": [
        {
            "strand_number": "1.0",
            "strand_name": "Living Things and their Environment",
            "substrands": [
                {
                    "substrand_number": "1.1",
                    "substrand_name": "Classification of Plants",
                    "number_of_lessons": 14,
                    "specific_learning_outcomes": [
                        "Classify plants into flowering and non-flowering",
                        "Describe functions of parts of a flower",
                        "Outline the importance of flowers in nature",
                        "Appreciate the importance of flowers in nature"
                    ],
                    "suggested_learning_experiences": [
                        "Use print and non-print materials to search for images of flowering and non-flowering plants and share",
                        "Take a walk in their locality to observe, identify and categorise plants into flowering and non-flowering",
                        "Draw a flower and label parts",
                        "Discuss functions of parts of a flower and share with peers",
                        "Discuss the importance of flowers in nature with peers",
                        "Use digital applications to draw, paint and label flowers"
                    ],
                    "key_inquiry_questions": [
                        "How are plants classified?"
                    ],
                    "core_competencies": [
                        "Creativity and imagination: The learner reflects and draws accurate images as they draw a flower and label parts",
                        "Digital literacy: The learner acquires digital manipulative skills as they use digital applications to draw, paint and label flowers"
                    ],
                    "values": [
                        "Unity: The learner appreciates sharing of the available resources amicably as they draw a flower and label parts"
                    ],
                    "pcis": [
                        "Environmental Conservation: The learner conserves the environment by not destroying plants as they observe, identify and categorise plants into flowering and non-flowering in their natural habitat"
                    ],
                    "links_to_other_subjects": [
                        "Creative Arts: The use of digital applications to draw, paint and label flowers is linked to drawing and painting in Creative Arts"
                    ]
                },
                {
                    "substrand_number": "1.2",
                    "substrand_name": "Invertebrates",
                    "number_of_lessons": 16,
                    "specific_learning_outcomes": [
                        "Describe general characteristics of vertebrates",
                        "Classify vertebrates into their main groups",
                        "Appreciate the importance of vertebrates in the environment"
                    ],
                    "suggested_learning_experiences": [
                        "Search for information from print and non-print material on the general characteristics of vertebrates and share with peers",
                        "Explore the school compound and adjacent environment to observe and identify characteristics of vertebrates",
                        "Discuss with peers the characteristics of different groups of vertebrates, study their main characteristics",
                        "Project: Making a portfolio of different categories of vertebrates in their locality"
                    ],
                    "key_inquiry_questions": [
                        "What are the key features of vertebrates?"
                    ],
                    "core_competencies": [
                        "Communication and collaboration: The learner acquires speaking and listening skills as they contribute in the discussions on main characteristics of vertebrates",
                        "Creativity and Imagination: The learner acquires manipulative skills as they skilfully designs and develops a portfolio on vertebrates"
                    ],
                    "values": [
                        "Responsibility: The learner observes safety precautions when handling different animals"
                    ],
                    "pcis": [
                        "Safety and security: The learner observes necessary precautions while handling animals"
                    ],
                    "links_to_other_subjects": [
                        "Agriculture and Nutrition: The learner links information on characteristics of animals as living things to the study of livestock in Agriculture",
                        "Creative Arts: Making of a portfolio of different categories of vertebrates is linked to designing in Creative Arts"
                    ]
                },
                {
                    "substrand_number": "1.3",
                    "substrand_name": "The Human Breathing System",
                    "number_of_lessons": 18,
                    "specific_learning_outcomes": [
                        "Identify the main parts of the human breathing system",
                        "Describe the functions of parts of the human breathing system",
                        "Outline the symptoms and prevention measures for common conditions and diseases of the breathing system",
                        "Appreciate the need for maintaining a healthy breathing system"
                    ],
                    "suggested_learning_experiences": [
                        "Use print and non-print material to identify the human breathing system",
                        "Draw the human breathing system and label the main parts",
                        "Use print or non-print media to search for information on the functions of main parts of the human breathing system and share with peers",
                        "Discuss symptoms and prevention of common conditions and diseases that affect the human breathing system and share",
                        "Use simulation or digital images to illustrate major parts of the human breathing system",
                        "Project: Learners are guided to make models of the human breathing system using locally available materials"
                    ],
                    "key_inquiry_questions": [
                        "What makes up the human breathing system?",
                        "What enhances a healthy breathing system?"
                    ],
                    "core_competencies": [
                        "Creativity and Imagination: The learner reflects on appropriate images as they design different ways of modelling the human breathing system using locally available material",
                        "Digital literacy: The learner acquires digital manipulative skills as they use simulations or digital images to illustrate major parts of the human breathing system"
                    ],
                    "values": [
                        "Love: The learner develops caring attitude towards self and others health as they discuss symptoms and prevention of common conditions and diseases that affect the human breathing system",
                        "Responsibility: The learner shows accountability in protecting self and others as they study prevention of common conditions and diseases that affect the human breathing system"
                    ],
                    "pcis": [
                        "Preventive health and communicable diseases: The learner learns how to prevent diseases as they discuss symptoms and prevention of common conditions and diseases that affect the human breathing system"
                    ],
                    "links_to_other_subjects": [
                        "Agriculture and Nutrition: The information on symptoms and prevention of common conditions and diseases that affect the human breathing system is linked to personal hygiene in Agriculture and Nutrition"
                    ]
                }
            ]
        },
        {
            "strand_number": "2.0",
            "strand_name": "Matter",
            "substrands": [
                {
                    "substrand_number": "2.1",
                    "substrand_name": "Mixtures",
                    "number_of_lessons": 14,
                    "specific_learning_outcomes": [
                        "Classify mixtures as homogeneous or heterogeneous",
                        "Apply appropriate methods to separate heterogeneous mixtures",
                        "Outline the applications of separating mixtures in day-to-day life",
                        "Appreciate different methods of separating mixtures in day-to-day life"
                    ],
                    "suggested_learning_experiences": [
                        "Brainstorm on the meaning of a mixture, give examples at home and school",
                        "Carry out activities to categorise mixtures as homogeneous (uniform) and heterogeneous (non-uniform)",
                        "Carry out activities to separate heterogeneous mixtures",
                        "Carry out activities to demonstrate ways of separating mixtures in day-to-day life"
                    ],
                    "key_inquiry_questions": [
                        "What are the applications of mixture separation in day-to-day life?"
                    ],
                    "core_competencies": [
                        "Critical thinking and imagination: The learner reflects on the best ways of separating different mixtures as they carry out activities to demonstrate ways of separating mixtures",
                        "Learning to learn: The learner learns new methods of separating mixtures through their own experiences as they carry out activities with peers to separate different types of mixtures"
                    ],
                    "values": [
                        "Social justice: The learner gives others equal opportunities in sharing responsibilities as they carry out activities to separate heterogeneous mixtures"
                    ],
                    "pcis": [
                        "Health Issues: The learner learns how to separate mixtures to remove impurities in cleaning of water for domestic usage as they carry out activities to demonstrate ways of separating mixtures"
                    ],
                    "links_to_other_subjects": [
                        "Agriculture and Nutrition: The learner applies the knowledge on separating mixtures in agricultural processes like straining milk, winnowing grains and straining honey"
                    ]
                },
                {
                    "substrand_number": "2.2",
                    "substrand_name": "Water Pollution",
                    "number_of_lessons": 18,
                    "specific_learning_outcomes": [
                        "Identify water pollutants in the water sources",
                        "Outline the effects of water pollution in day-to-day life",
                        "Identify methods of reducing water pollution in the water sources",
                        "Apply appropriate methods of water treatment",
                        "Advocate for safe water sources in the locality"
                    ],
                    "suggested_learning_experiences": [
                        "Brainstorm on water pollutants in water sources",
                        "Discuss with peers the effects of water pollution in day-to-day life",
                        "Discuss with peers the different methods of reducing water pollution",
                        "Observe safety measures when working in a water-polluted environment (Example: practise use of gumboots and gloves)",
                        "Carry out activities to demonstrate methods of water treatment",
                        "Use visual aids or digital devices to identify water pollutants and their effects in day-to-day life",
                        "Project: Learners to make functional water filters using locally available materials"
                    ],
                    "key_inquiry_questions": [
                        "What are the dangers of water pollution?"
                    ],
                    "core_competencies": [
                        "Creativity and imagination: The learner reflects and comes up with new ideas in making functional water filters using locally available materials"
                    ],
                    "values": [
                        "Responsibility: The learner practices being responsible in playing different roles as they carry out activities to demonstrate methods of water treatment",
                        "Peace: The learner learns how to share available materials amicably as they carry out activities to demonstrate methods of water treatment"
                    ],
                    "pcis": [
                        "Health Issues: The learner practices health preventive measures on water-borne diseases as they carry out activities to demonstrate basic methods of water treatment"
                    ],
                    "links_to_other_subjects": [
                        "Agriculture and Nutrition: Knowledge and skills on ways of reducing pollutants are used to obtain clean water for domestic use in Agriculture and Nutrition"
                    ]
                }
            ]
        },
        {
            "strand_number": "3.0",
            "strand_name": "Force and Energy",
            "substrands": [
                {
                    "substrand_number": "3.1",
                    "substrand_name": "Floating and Sinking",
                    "number_of_lessons": 14,
                    "specific_learning_outcomes": [
                        "Classify objects as floating or sinking in water",
                        "Identify factors that affect floating and sinking of objects in water",
                        "Explain applications of floating and sinking in day-to-day life",
                        "Appreciate the use of floaters as life savers"
                    ],
                    "suggested_learning_experiences": [
                        "Carry out activities using different objects to demonstrate floating and sinking in water (use dry wood, stone, metals, plastic, cork, buoy and feathers)",
                        "Carry out activities to classify objects into those that float and those that sink in water",
                        "Carry out activities to show how shape, weight and size affect floating and sinking of objects in water",
                        "Discuss with peers the applications of floating and sinking in day-to-day life (swimming, diving, use of lifesavers, water transport, floods, drowning, surfing)",
                        "Use digital or print media to search for effects of flooding and the use of floaters as life savers",
                        "Project: Learners to make lifesaving floaters from locally available materials"
                    ],
                    "key_inquiry_questions": [
                        "Why do some materials float and others sink?",
                        "How are floaters useful in day-to-day life?"
                    ],
                    "core_competencies": [
                        "Communication and Collaboration: The learner acquires spirit of teamwork while carrying out activities to observe and classify objects into those that float and those that sink in water",
                        "Critical thinking and problem solving: The learner explores a variety of locally available materials that can be used to make lifesaving floaters"
                    ],
                    "values": [
                        "Integrity: The learner gives honest observations and records real results while carrying out activities to classify objects into those that float or sink in water",
                        "Responsibility: The learner plays different roles as they carry out activities to make lifesaving floaters from locally available materials"
                    ],
                    "pcis": [
                        "Disaster Risk Reduction: The learner learns how to contribute in water lifesaving strategies as they carry out activities to make lifesaving floaters from locally available materials"
                    ],
                    "links_to_other_subjects": [
                        "Agriculture and Nutrition: The learner relates the concept of floating and sinking to fish farming and irrigation in Agriculture and Nutrition"
                    ]
                },
                {
                    "substrand_number": "3.2",
                    "substrand_name": "Sound Energy",
                    "number_of_lessons": 14,
                    "specific_learning_outcomes": [
                        "Identify sources of sound in nature",
                        "Demonstrate the movement of sound in nature",
                        "Describe effects of loud sound in day-to-day life",
                        "Appreciate the role of sound in day-to-day life"
                    ],
                    "suggested_learning_experiences": [
                        "Carry out activities to identify sources of sound",
                        "Carry out an activity to demonstrate that sound travels in all directions from a source (listening to a loud sound from a common speaker from different directions and around corners)",
                        "Carry out an activity to demonstrate reflection of sound; echo (use of two tubes placed alongside a wall, a cliff, a large hall, a forest, a valley, between tall buildings)",
                        "Discuss with peers the effects of loud sound in the environment",
                        "Use digital or print media to search for the effects of loud sound in day-to-day life",
                        "Discuss the role of the government in addressing sound pollution",
                        "Project 1: Learners to make a sound-producing instrument from locally available materials (for example: bell, drum, guitar, wind instruments, etc.)",
                        "Project 2: Create a sound game using Scratch"
                    ],
                    "key_inquiry_questions": [
                        "How is sound produced?",
                        "What are the effects of loud sound?"
                    ],
                    "core_competencies": [
                        "Creativity and Imagination: The learner experiments different ways of making sound-producing instruments using locally available materials",
                        "Digital literacy: The learner acquires digital manipulative skills as they use appropriate digital technology to create and add sound effects using the Sound blocks in Scratch"
                    ],
                    "values": [
                        "Responsibility: The learner learns how to minimise the effects of loud sound in the environment as they discuss with peers the effects of loud sound in the environment"
                    ],
                    "pcis": [
                        "Citizenship: The learner acquires awareness on human rights and responsibilities as they discuss the role of the government in addressing sound pollution",
                        "Socio-Economic Issues: The learner creates awareness on sound pollution as they discuss with peers the effects of loud sound in the environment"
                    ],
                    "links_to_other_subjects": [
                        "Creative Arts: The learner relates the concept of sources of sound to making musical instruments"
                    ]
                },
                {
                    "substrand_number": "3.3",
                    "substrand_name": "Heat Transfer",
                    "number_of_lessons": 12,
                    "specific_learning_outcomes": [
                        "Demonstrate the modes of heat transfer in nature",
                        "Classify conductors of heat into good or poor conductors",
                        "Explain the uses of heat transfer in day-to-day life",
                        "Acknowledge safety precautions when handling heat"
                    ],
                    "suggested_learning_experiences": [
                        "Brainstorm on the meanings of the terms conduction, convection and radiation as used in heat transfer",
                        "Perform experiments to demonstrate the modes of heat transfer",
                        "Carry out experiments to identify good and poor conductors of heat",
                        "Discuss with peers applications of heat transfer in day-to-day life (cooking, melting, freezing, maintaining body temperature, insulation)",
                        "Use digital or print media to search for applications of heat transfer in day-to-day life",
                        "Discuss with peers safety precautions when handling heat",
                        "Discuss with peers various ways of responding to fire emergencies",
                        "Project 1: Learners to make oven gloves using locally available materials",
                        "Project 2: Learners to make a fireless cooker"
                    ],
                    "key_inquiry_questions": [
                        "How is heat transferred through materials in nature?"
                    ],
                    "core_competencies": [
                        "Self-efficacy: The learner displays self-confidence as they perform experiments to demonstrate the modes of heat transfer"
                    ],
                    "values": [
                        "Social justice: The learner practices sharing of resources equitably as they perform experiments to identify good and poor conductors of heat"
                    ],
                    "pcis": [
                        "Social-Economic Issues: The learner exercises fire emergency response measures as they discuss various ways of responding to fire emergencies"
                    ],
                    "links_to_other_subjects": [
                        "Agriculture and Nutrition: The learner links the concept of heat transfer in choosing of appropriate material for knitting the oven gloves"
                    ]
                }
            ]
        }
    ]
}